setup.py
psypg/__init__.py
psypg/psypg_wrap.py
psypg.egg-info/PKG-INFO
psypg.egg-info/SOURCES.txt
psypg.egg-info/dependency_links.txt
psypg.egg-info/requires.txt
psypg.egg-info/top_level.txt