Metadata-Version: 1.0
Name: psypg
Version: 1.0
Summary: Simple Python wrapper for Psycopg2
Home-page: https://github.com/gwchamb/psypg
Author: Gary Chambers
Author-email: gwc@gwcmail.com
License: UNKNOWN
Platform: UNKNOWN
